chpass/__init__.py
chpass/__main__.py
chpass/cli.py
chpass/config.py
chpass/core/__init__.py
chpass/core/object_factory.py
chpass/core/interfaces/__init__.py
chpass/core/interfaces/file_adapter_interface.py
chpass/dal/__init__.py
chpass/dal/chrome_db_adapter.py
chpass/dal/db_connection.py
chpass/dal/session.py
chpass/dal/db_adapters/__init__.py
chpass/dal/db_adapters/history_db_adapter.py
chpass/dal/db_adapters/logins_db_adapter.py
chpass/dal/db_adapters/top_sites_db_adapter.py
chpass/dal/models/__init__.py
chpass/dal/models/base.py
chpass/dal/models/download.py
chpass/dal/models/history.py
chpass/dal/models/login.py
chpass/dal/models/topSite.py
chpass/dal/table_adapters/__init__.py
chpass/dal/table_adapters/downloads_table_adapter.py
chpass/dal/table_adapters/history_table_adapter.py
chpass/dal/table_adapters/logins_table_adapter.py
chpass/dal/table_adapters/top_sites_table_adapter.py
chpass/exceptions/__init__.py
chpass/exceptions/chrome_not_installed_exception.py
chpass/exceptions/chrome_profile_not_found_exception.py
chpass/exceptions/file_adapter_not_supported_exception.py
chpass/exceptions/login_not_found_exception.py
chpass/exceptions/operating_system_not_supported.py
chpass/exceptions/user_not_found_exception.py
chpass/services/__init__.py
chpass/services/bytes.py
chpass/services/chrome.py
chpass/services/path.py
chpass/services/file_adapters/__init__.py
chpass/services/file_adapters/csv_file_adapter.py
chpass/services/file_adapters/json_file_adapter.py
chpass-0.4.2.dist-info/licenses/LICENSE
tests/__init__.py
tests/integration/__init__.py
tests/integration/conftest.py
tests/integration/test_export_all_data.py
tests/integration/test_export_downloads.py
tests/integration/test_export_history.py
tests/integration/test_export_passwords.py
tests/integration/test_export_profile_picture.py
tests/integration/test_export_top_sites.py
tests/integration/test_import_passwords.py
tests/integration/test_path.py
tests/integration/test_profile_picture.py
tests/integration/dal/__init__.py
chpass-0.4.2.dist-info/METADATA
chpass-0.4.2.dist-info/WHEEL
chpass-0.4.2.dist-info/entry_points.txt
chpass-0.4.2.dist-info/top_level.txt
chpass-0.4.2.dist-info/RECORD
