Metadata-Version: 2.4
Name: chpass
Version: 0.4.2
Summary: Gather information from chrome
Home-page: https://github.com/bengabay11/chpass
Author: Ben Gabay
Author-email: ben.gabay38@gmail.com
License: License :: OSI Approved :: MIT License
Keywords: chrome passwords
Classifier: Programming Language :: Python :: 3
Classifier: License :: OSI Approved :: MIT License
Classifier: Operating System :: OS Independent
Requires-Python: >=3
License-File: LICENSE
Requires-Dist: pattern-singleton==1.2.0
Requires-Dist: sqlalchemy==2.0.31
Requires-Dist: pandas==2.2.0
Dynamic: author
Dynamic: author-email
Dynamic: classifier
Dynamic: description
Dynamic: description-content-type
Dynamic: home-page
Dynamic: keywords
Dynamic: license
Dynamic: license-file
Dynamic: requires-dist
Dynamic: requires-python
Dynamic: summary
